litequery/__init__.py
litequery/cli.py
litequery/config.py
litequery/core.py
litequery/migrations.py
litequery/shell.py
litequery-0.7.4.dist-info/METADATA
litequery-0.7.4.dist-info/WHEEL
litequery-0.7.4.dist-info/entry_points.txt
litequery-0.7.4.dist-info/licenses/LICENSE
litequery-0.7.4.dist-info/RECORD
