Metadata-Version: 2.4
Name: litequery
Version: 0.7.4
Summary: A handy way to interact with an SQLite database from Python
Project-URL: Homepage, https://github.com/imryche/litequery
Project-URL: Issues, https://github.com/imryche/litequery/issues
Author-email: Dima Charnyshou <imryche13@gmail.com>
License-File: LICENSE
Classifier: License :: OSI Approved :: MIT License
Classifier: Operating System :: OS Independent
Classifier: Programming Language :: Python :: 3
Requires-Python: >=3.11
Requires-Dist: aiosqlite
Requires-Dist: sqlparse>=0.5.3
